{"image":{"full":"Soraka.png","sprite":"champion3.png","group":"champion","x":192,"y":48,"w":48,"h":48},"lore":"Soraka, una nómada proveniente de las dimensiones celestiales más allá del monte Targon, dejó a un lado su inmortalidad para proteger a las razas mortales de sus propios instintos asesinos. Su cometido es difundir las virtudes de la compasión y la misericordia entre todos los seres con los que se cruza, e incluso sanar a aquellos que desean hacerle daño. Pese a los problemas que ha presenciado Soraka hasta la fecha, sigue creyendo firmemente que los pueblos de Runaterra no han alcanzado todo su potencial.","partype":"Maná","title":"La Hija de las Estrellas","blurb":"Soraka, una nómada proveniente de las dimensiones celestiales más allá del monte Targon, dejó a un lado su inmortalidad para proteger a las razas mortales de sus propios instintos asesinos. Su cometido es difundir las virtudes de la compasión y la...","allytips":["Soraka es una poderosa aliada en batalla, ya que utiliza hechizos de curación que ayudan al grupo.","Puedes utilizar Plegaria con tus aliados por todo el mapa para salvarlos de situaciones que de otro modo serían fatales.","Equinoccio se puede usar como una poderosa herramienta de control de zonas."],"passive":{"name":"Salvación","description":"Soraka corre más rápidamente hacia los aliados con poca vida.","sanitizedDescription":"Soraka corre más rápidamente hacia los aliados con poca vida.","image":{"full":"Soraka_Passive.png","sprite":"passive3.png","group":"passive","x":192,"y":48,"w":48,"h":48}},"tags":["Support","Mage"],"recommended":[{"champion":"Soraka","title":"Beginner","type":"riot","map":"SR","mode":"INTRO","blocks":[{"type":"beginner_starter","recMath":false,"items":[{"id":1056,"count":1}]},{"type":"beginner_starter","recMath":false,"items":[{"id":1056,"count":1},{"id":2003,"count":1}]},{"type":"beginner_advanced","recMath":true,"items":[{"id":1028,"count":1},{"id":1027,"count":1},{"id":3010,"count":1}]},{"type":"beginner_movementspeed","recMath":true,"items":[{"id":1001,"count":1},{"id":3020,"count":1}]},{"type":"beginner_legendaryitem","recMath":true,"items":[{"id":3010,"count":1},{"id":1026,"count":1},{"id":3027,"count":1}]},{"type":"beginner_morelegendaryitems","recMath":false,"items":[{"id":3174,"count":1},{"id":3116,"count":1},{"id":3089,"count":1},{"id":3504,"count":1}]}]},{"champion":"Soraka","title":"SorakaARAM","type":"riot","map":"HA","mode":"ARAM","blocks":[{"type":"starting","recMath":false,"items":[{"id":3112,"count":1},{"id":1001,"count":1},{"id":2003,"count":3}]},{"type":"essential","recMath":false,"items":[{"id":3107,"count":1},{"id":3190,"count":1},{"id":3158,"count":1}]},{"type":"offensive","recMath":false,"items":[{"id":3504,"count":1},{"id":3174,"count":1},{"id":3089,"count":1}]},{"type":"defensive","recMath":false,"items":[{"id":3102,"count":1},{"id":3083,"count":1},{"id":3157,"count":1}]},{"type":"consumables","recMath":false,"items":[{"id":2003,"count":1},{"id":2139,"count":1}]}]},{"champion":"Soraka","title":"SorakaCS","type":"riot","map":"CrystalScar","mode":"ODIN","blocks":[{"type":"starting","recMath":false,"items":[{"id":2003,"count":3},{"id":3301,"count":1},{"id":3340,"count":1}]},{"type":"early","recMath":false,"items":[{"id":2049,"count":1},{"id":3096,"count":1},{"id":1001,"count":1}]},{"type":"essential","recMath":false,"items":[{"id":3069,"count":1},{"id":3050,"count":1},{"id":3158,"count":1}]},{"type":"aggressive","recMath":false,"items":[{"id":3504,"count":1},{"id":3089,"count":1},{"id":3060,"count":1}]},{"type":"protective","recMath":false,"items":[{"id":3222,"count":1},{"id":3190,"count":1},{"id":3107,"count":1}]},{"type":"consumables","recMath":false,"items":[{"id":2003,"count":1},{"id":2055,"count":1},{"id":2139,"count":1}]}]},{"champion":"Soraka","title":"SorakaFIRSTBLOOD","type":"riot","map":"HA","mode":"FIRSTBLOOD","blocks":[{"type":"starting","recMath":false,"items":[{"id":2003,"count":3},{"id":3301,"count":1},{"id":3340,"count":1}]},{"type":"early","recMath":false,"items":[{"id":2049,"count":1},{"id":3096,"count":1},{"id":1001,"count":1}]},{"type":"essential","recMath":false,"items":[{"id":3069,"count":1},{"id":3050,"count":1},{"id":3158,"count":1}]},{"type":"aggressive","recMath":false,"items":[{"id":3504,"count":1},{"id":3089,"count":1},{"id":3060,"count":1}]},{"type":"protective","recMath":false,"items":[{"id":3222,"count":1},{"id":3190,"count":1},{"id":3107,"count":1}]},{"type":"consumables","recMath":false,"items":[{"id":2003,"count":1},{"id":2139,"count":1}]}]},{"champion":"Soraka","title":"SorakaKINGPORO","type":"riot","map":"HA","mode":"KINGPORO","blocks":[{"type":"KingPoroSnax","recMath":false,"items":[{"id":3680,"count":1},{"id":3681,"count":1},{"id":3682,"count":1},{"id":3683,"count":1}]},{"type":"starting","recMath":false,"items":[{"id":2051,"count":1},{"id":3301,"count":1},{"id":2003,"count":2}]},{"type":"essential","recMath":false,"items":[{"id":3069,"count":1},{"id":3190,"count":1},{"id":3158,"count":1}]},{"type":"offensive","recMath":false,"items":[{"id":3504,"count":1},{"id":3050,"count":1},{"id":3089,"count":1}]},{"type":"defensive","recMath":false,"items":[{"id":3107,"count":1},{"id":3083,"count":1},{"id":3102,"count":1},{"id":3157,"count":1}]},{"type":"consumables","recMath":false,"items":[{"id":2003,"count":1},{"id":2139,"count":1}]}]},{"champion":"Soraka","title":"SorakaSG","type":"riot","map":"CityPark","mode":"STARGUARDIAN","blocks":[{"type":"starting","recMath":false,"items":[{"id":3301,"count":1},{"id":2003,"count":3},{"id":3340,"count":1}]},{"type":"early","recMath":false,"items":[{"id":2049,"count":1},{"id":3096,"count":1},{"id":1001,"count":1}]},{"type":"essential","recMath":false,"items":[{"id":3069,"count":1},{"id":3107,"count":1},{"id":3158,"count":1}]},{"type":"aggressive","recMath":false,"items":[{"id":3504,"count":1},{"id":3089,"count":1},{"id":3102,"count":1}]},{"type":"protective","recMath":false,"items":[{"id":3222,"count":1},{"id":3190,"count":1},{"id":3109,"count":1}]},{"type":"consumables","recMath":false,"items":[{"id":2003,"count":1},{"id":2055,"count":1},{"id":2139,"count":1}]}]},{"champion":"Soraka","title":"SorakaSIEGE","type":"riot","map":"SR","mode":"SIEGE","blocks":[{"type":"siegeOffense","recMath":false,"items":[{"id":3631,"count":1},{"id":3641,"count":1},{"id":3647,"count":1},{"id":3635,"count":1},{"id":3642,"count":1}]},{"type":"siegeDefense","recMath":false,"items":[{"id":3634,"count":1},{"id":3640,"count":1},{"id":3643,"count":1},{"id":3636,"count":1},{"id":3642,"count":1}]},{"type":"essential","recMath":false,"items":[{"id":3069,"count":1},{"id":3050,"count":1},{"id":3158,"count":1}]},{"type":"aggressive","recMath":false,"items":[{"id":3504,"count":1},{"id":3089,"count":1},{"id":3060,"count":1}]},{"type":"protective","recMath":false,"items":[{"id":3222,"count":1},{"id":3190,"count":1},{"id":3107,"count":1}]}]},{"champion":"Soraka","title":"SorakaSR","type":"riot","map":"SR","mode":"CLASSIC","blocks":[{"type":"starting","recMath":false,"items":[{"id":3303,"count":1},{"id":2003,"count":3},{"id":3340,"count":1}]},{"type":"early","recMath":false,"items":[{"id":3098,"count":1},{"id":1001,"count":1}]},{"type":"essential","recMath":false,"items":[{"id":3092,"count":1},{"id":3107,"count":1},{"id":3158,"count":1}]},{"type":"aggressive","recMath":false,"items":[{"id":3504,"count":1},{"id":3905,"count":1},{"id":3102,"count":1}]},{"type":"protective","recMath":false,"items":[{"id":3222,"count":1},{"id":3190,"count":1},{"id":3109,"count":1}]},{"type":"consumables","recMath":false,"items":[{"id":2003,"count":1},{"id":2139,"count":1}]}]},{"champion":"Soraka","title":"SorakaTT","type":"riot","map":"TT","mode":"CLASSIC","blocks":[{"type":"starting","recMath":false,"items":[{"id":1001,"count":1},{"id":3304,"count":1},{"id":2003,"count":4}]},{"type":"essential","recMath":false,"items":[{"id":3306,"count":1},{"id":3158,"count":1}]},{"type":"offensive","recMath":false,"items":[{"id":3090,"count":1},{"id":3050,"count":1},{"id":3504,"count":1}]},{"type":"defensive","recMath":false,"items":[{"id":3107,"count":1},{"id":3170,"count":1},{"id":3222,"count":1},{"id":3060,"count":1}]},{"type":"consumables","recMath":false,"items":[{"id":2003,"count":1},{"id":2139,"count":1}]}]}],"skins":[{"id":16000,"name":"default","num":0},{"id":16001,"name":"Soraka dríade","num":1},{"id":16002,"name":"Soraka divina","num":2},{"id":16003,"name":"Soraka celestial","num":3},{"id":16004,"name":"Soraka segadora de almas","num":4},{"id":16005,"name":"Soraka Orden del Plátano","num":5},{"id":16006,"name":"Programa Soraka","num":6},{"id":16007,"name":"Soraka guardiana de las estrellas","num":7}],"stats":{"armor":32.0,"armorperlevel":3.8,"attackdamage":50.04,"attackdamageperlevel":3.0,"attackrange":550.0,"attackspeedoffset":0.0,"attackspeedperlevel":2.14,"crit":0.0,"critperlevel":0.0,"hp":529.04,"hpperlevel":78.0,"hpregen":2.5,"hpregenperlevel":0.5,"movespeed":325.0,"mp":350.8,"mpperlevel":60.0,"mpregen":11.5,"mpregenperlevel":0.4,"spellblock":30.0,"spellblockperlevel":0.5},"enemytips":["Si durante un combate en equipo Soraka se acerca a la vanguardia, concéntrate en ella.","Si utiliza Equinoccio como herramienta de hostigamiento, aprovéchate de su dilatado enfriamiento.","Es más fácil atacarla a ella que al aliado al que está curando."],"name":"Soraka","id":16,"spells":[{"name":"Invocación estelar","description":"Del cielo cae una estrella en la zona objetivo que causa daño mágico y ralentiza a los enemigos. Si Soraka alcanza a un campeón enemigo con Invocación estelar, recupera vida y obtiene velocidad de movimiento cuando se aleja de los campeones enemigos.","sanitizedDescription":"Del cielo cae una estrella en la zona objetivo que causa daño mágico y ralentiza a los enemigos. Si Soraka alcanza a un campeón enemigo con Invocación estelar, recupera vida y obtiene velocidad de movimiento cuando se aleja de los campeones enemigos.","tooltip":"Soraka lanza una estrella sobre un punto. Los enemigos situados en el radio de la explosión reciben {{ e1 }} <span class=\"color99FF99\">(+{{ a1 }})</span> de daño mágico y se ralentizan un {{ e2 }}% durante 2 s.<br /><br />Si Invocación estelar alcanza a un campeón, Soraka recibe <span class=\"colorDDDDDD\">Rejuvenecimiento</span> durante {{ e5 }} s y recupera hasta {{ e3 }} <span class=\"color99FF99\">(+{{ f1 }})</span> de vida por segundo. Además, otorga un {{ e9 }}% de velocidad de movimiento al no avanzar hacia campeones enemigos.","sanitizedTooltip":"Soraka lanza una estrella sobre un punto. Los enemigos situados en el radio de la explosión reciben {{ e1 }} (+{{ a1 }}) de daño mágico y se ralentizan un {{ e2 }}% durante 2 s. Si Invocación estelar alcanza a un campeón, Soraka recibe Rejuvenecimiento durante {{ e5 }} s y recupera hasta {{ e3 }} (+{{ f1 }}) de vida por segundo. Además, otorga un {{ e9 }}% de velocidad de movimiento al no avanzar hacia campeones enemigos.","leveltip":{"label":["Daño","Recuperación de vida (Rejuvenecimiento)","Duración del rejuvenecimiento (para aliados)","Coste de maná"],"effect":["{{ e1 }} -> {{ e1NL }}","{{ e3 }} -> {{ e3NL }}","{{ e6 }} -> {{ e6NL }}","{{ cost }} -> {{ costNL }}"]},"image":{"full":"SorakaQ.png","sprite":"spell10.png","group":"spell","x":192,"y":144,"w":48,"h":48},"resource":"{{ cost }} de maná","maxrank":5,"cost":[40,45,50,55,60],"costType":" de maná","costBurn":"40/45/50/55/60","cooldown":[5.0,5.0,5.0,5.0,5.0],"cooldownBurn":"5","effect":[null,[70.0,110.0,150.0,190.0,230.0],[30.0,30.0,30.0,30.0,30.0],[14.0,16.0,18.0,20.0,22.0],[7.0,9.0,11.0,13.0,15.0],[4.0,4.0,4.0,4.0,4.0],[3.0,3.5,4.0,4.5,5.0],[0.1,0.1,0.1,0.1,0.1],[0.05,0.05,0.05,0.05,0.05],[10.0,10.0,10.0,10.0,10.0],[0.0,0.0,0.0,0.0,0.0]],"effectBurn":["","70/110/150/190/230","30","14/16/18/20/22","7/9/11/13/15","4","3/3.5/4/4.5/5","0.1","0.05","10","0"],"vars":[{"key":"a1","link":"spelldamage","coeff":[0.35]}],"range":[810,810,810,810,810],"rangeBurn":"810","key":"SorakaQ"},{"name":"Inyección astral","description":"Soraka sacrifica parte de su vida para curar a otro campeón aliado.","sanitizedDescription":"Soraka sacrifica parte de su vida para curar a otro campeón aliado.","tooltip":"Restaura {{ e1 }} <span class=\"color99FF99\">(+{{ a1 }})</span> de vida a otro campeón aliado.<br /><br />Si se lanza cuando tiene el efecto de <span class=\"colorDDDDDD\">Rejuvenecimiento</span>, Soraka transferirá el efecto a su objetivo durante {{ f1 }} s.<br /><br /><span class=\"color919191\"><i>No se puede lanzar si Soraka tiene menos del 5% de vida.</i></span>","sanitizedTooltip":"Restaura {{ e1 }} (+{{ a1 }}) de vida a otro campeón aliado. Si se lanza cuando tiene el efecto de Rejuvenecimiento, Soraka transferirá el efecto a su objetivo durante {{ f1 }} s. No se puede lanzar si Soraka tiene menos del 5% de vida.","leveltip":{"label":["Magnitud de curación","Enfriamiento","Coste de maná"],"effect":["{{ e1 }} -> {{ e1NL }}","{{ cooldown }} -> {{ cooldownNL }}","{{ cost }} -> {{ costNL }}"]},"image":{"full":"SorakaW.png","sprite":"spell10.png","group":"spell","x":240,"y":144,"w":48,"h":48},"resource":"10% vida máxima, {{ cost }} de maná","maxrank":5,"cost":[50,55,60,65,70],"costType":" de maná","costBurn":"50/55/60/65/70","cooldown":[8.0,6.5,5.0,3.5,2.0],"cooldownBurn":"8/6.5/5/3.5/2","effect":[null,[80.0,110.0,140.0,170.0,200.0],[0.1,0.1,0.1,0.1,0.1],[0.0,0.0,0.0,0.0,0.0],[0.0,0.0,0.0,0.0,0.0],[0.0,0.0,0.0,0.0,0.0],[0.0,0.0,0.0,0.0,0.0],[0.0,0.0,0.0,0.0,0.0],[0.0,0.0,0.0,0.0,0.0],[0.0,0.0,0.0,0.0,0.0],[0.0,0.0,0.0,0.0,0.0]],"effectBurn":["","80/110/140/170/200","0.1","0","0","0","0","0","0","0","0"],"vars":[{"key":"a1","link":"spelldamage","coeff":[0.6]}],"range":[550,550,550,550,550],"rangeBurn":"550","key":"SorakaW"},{"name":"Equinoccio","description":"Crea una zona que silencia a todos los enemigos situados en su interior. Una vez que expira el efecto, los afectados quedan inmovilizados.","sanitizedDescription":"Crea una zona que silencia a todos los enemigos situados en su interior. Una vez que expira el efecto, los afectados quedan inmovilizados.","tooltip":"Crea una zona de silencio que dura 1,5 s y causa {{ e2 }} <span class=\"color99FF99\">(+{{ a1 }})</span> de daño mágico a los campeones enemigos. Los enemigos que permanecen en la zona quedan silenciados hasta que se marchan.<br /><br />Cuando la zona desaparece, los enemigos situados en ella quedan inmovilizados durante {{ e1 }} s y reciben {{ e2 }} <span class=\"color99FF99\">(+{{ a1 }})</span> de daño mágico.","sanitizedTooltip":"Crea una zona de silencio que dura 1,5 s y causa {{ e2 }} (+{{ a1 }}) de daño mágico a los campeones enemigos. Los enemigos que permanecen en la zona quedan silenciados hasta que se marchan. Cuando la zona desaparece, los enemigos situados en ella quedan inmovilizados durante {{ e1 }} s y reciben {{ e2 }} (+{{ a1 }}) de daño mágico.","leveltip":{"label":["Daño","Enfriamiento","Duración de la inmovilización"],"effect":["{{ e2 }} -> {{ e2NL }}","{{ cooldown }} -> {{ cooldownNL }}","{{ e1 }} -> {{ e1NL }}"]},"image":{"full":"SorakaE.png","sprite":"spell10.png","group":"spell","x":288,"y":144,"w":48,"h":48},"resource":"{{ cost }} de maná","maxrank":5,"cost":[70,70,70,70,70],"costType":" de maná","costBurn":"70","cooldown":[24.0,22.0,20.0,18.0,16.0],"cooldownBurn":"24/22/20/18/16","effect":[null,[1.0,1.25,1.5,1.75,2.0],[70.0,110.0,150.0,190.0,230.0],[40.0,70.0,100.0,130.0,160.0],[5.0,5.0,5.0,5.0,5.0],[20.0,40.0,60.0,80.0,100.0],[60.0,90.0,120.0,150.0,180.0],[1.5,1.5,1.5,1.5,1.5],[260.0,260.0,260.0,260.0,260.0],[0.0,0.0,0.0,0.0,0.0],[0.0,0.0,0.0,0.0,0.0]],"effectBurn":["","1/1.25/1.5/1.75/2","70/110/150/190/230","40/70/100/130/160","5","20/40/60/80/100","60/90/120/150/180","1.5","260","0","0"],"vars":[{"key":"a1","link":"spelldamage","coeff":[0.4]},{"key":"a1","link":"spelldamage","coeff":[0.4]}],"range":[925,925,925,925,925],"rangeBurn":"925","key":"SorakaE"},{"name":"Plegaria","description":"Soraka infunde esperanza a sus aliados, lo que cura instantáneamente a los campeones amigos (incluida ella).","sanitizedDescription":"Soraka infunde esperanza a sus aliados, lo que cura instantáneamente a los campeones amigos (incluida ella).","tooltip":"Invoca los poderes divinos para restaurar {{ e1 }} <span class=\"color99FF99\">(+{{ a1 }})</span> puntos de vida a todos los campeones aliados. Plegaria es un 50% más efectiva sobre campeones con menos del 40% de vida.","sanitizedTooltip":"Invoca los poderes divinos para restaurar {{ e1 }} (+{{ a1 }}) puntos de vida a todos los campeones aliados. Plegaria es un 50% más efectiva sobre campeones con menos del 40% de vida.","leveltip":{"label":["Vida restaurada","Enfriamiento"],"effect":["{{ e1 }} -> {{ e1NL }}","{{ cooldown }} -> {{ cooldownNL }}"]},"image":{"full":"SorakaR.png","sprite":"spell10.png","group":"spell","x":336,"y":144,"w":48,"h":48},"resource":"{{ cost }} de maná","maxrank":3,"cost":[100,100,100],"costType":" de maná","costBurn":"100","cooldown":[160.0,145.0,130.0],"cooldownBurn":"160/145/130","effect":[null,[150.0,250.0,350.0],[120.0,90.0,60.0],[250.0,350.0,450.0],[1.5,1.5,1.5],[0.0,0.0,0.0],[0.0,0.0,0.0],[0.0,0.0,0.0],[0.0,0.0,0.0],[0.0,0.0,0.0],[0.0,0.0,0.0]],"effectBurn":["","150/250/350","120/90/60","250/350/450","1.5","0","0","0","0","0","0"],"vars":[{"key":"a1","link":"spelldamage","coeff":[0.55]}],"range":[25000,25000,25000],"rangeBurn":"25000","key":"SorakaR"}],"key":"Soraka","info":{"attack":2,"defense":5,"magic":7,"difficulty":3}}